{
  "db_name": "PostgreSQL",
  "query": "SELECT * FROM transactions WHERE id = $1 AND user_id = $2",
  "describe": {
    "columns": [
      {
        "ordinal": 0,
        "name": "id",
        "type_info": "Int4"
      },
      {
        "ordinal": 1,
        "name": "category",
        "type_info": "Varchar"
      },
      {
        "ordinal": 2,
        "name": "transactee",
        "type_info": "Varchar"
      },
      {
        "ordinal": 3,
        "name": "note",
        "type_info": "Varchar"
      },
      {
        "ordinal": 4,
        "name": "date",
        "type_info": "Date"
      },
      {
        "ordinal": 5,
        "name": "amount",
        "type_info": "Numeric"
      },
      {
        "ordinal": 6,
        "name": "user_id",
        "type_info": "Varchar"
      },
      {
        "ordinal": 7,
        "name": "tags",
        "type_info": "TextArray"
      }
    ],
    "parameters": {
      "Left": [
        "Int4",
        "Text"
      ]
    },
    "nullable": [
      false,
      false,
      true,
      true,
      false,
      false,
      false,
      false
    ]
  },
  "hash": "8a5c2158733d6037460d4434ca68221975cbf15a8b39b5848ebb6182023a5d4d"
}
